CHANGELOG.md
aws_data_tools/__init__.py
aws_data_tools/cli/TODO.md
aws_data_tools/cli/__init__.py
aws_data_tools/client/__init__.py
aws_data_tools/client/client.py
aws_data_tools/client/tests/test_client.py
aws_data_tools/conftest.py
aws_data_tools/fixtures/account_paths.txt
aws_data_tools/fixtures/dynamodb_item.json
aws_data_tools/fixtures/dynamodb_item_serialized.json
aws_data_tools/fixtures/ou_paths.txt
aws_data_tools/models/__init__.py
aws_data_tools/models/base.py
aws_data_tools/models/config.py
aws_data_tools/models/organizations.py
aws_data_tools/models/sns.py
aws_data_tools/models/sqs.py
aws_data_tools/models/tests/fixtures/config/item-change-notification.json
aws_data_tools/models/tests/fixtures/config/oversized-item-change-notification.json
aws_data_tools/models/tests/fixtures/config/periodic-rule.json
aws_data_tools/models/tests/fixtures/sns/notification.json
aws_data_tools/models/tests/fixtures/sqs/receive-message.json
aws_data_tools/models/tests/test_base.py
aws_data_tools/models/tests/test_organizations.py
aws_data_tools/utils/__init__.py
aws_data_tools/utils/dynamodb.py
aws_data_tools/utils/tags.py
aws_data_tools/utils/tests/test_dynamodb.py
aws_data_tools/utils/tests/test_tags.py
aws_data_tools/utils/validators.py
aws_data_tools-0.1.1.dist-info/entry_points.txt
aws_data_tools-0.1.1.dist-info/LICENSE
aws_data_tools-0.1.1.dist-info/WHEEL
aws_data_tools-0.1.1.dist-info/METADATA
aws_data_tools-0.1.1.dist-info/RECORD
