Metadata-Version: 2.1
Name: aws-data-tools
Version: 0.1.1
Summary: A set of Python libraries for querying and transforming data from AWS APIs
Home-page: https://timoguin.github.io/aws-data-tools-py
License: MIT
Keywords: aws,etl,library
Author: Tim O'Guin
Author-email: timoguin@gmail.com
Maintainer: Tim O'Guin
Maintainer-email: timoguin@gmail.com
Requires-Python: >=3.9,<4
Classifier: Development Status :: 4 - Beta
Classifier: Intended Audience :: Developers
Classifier: License :: OSI Approved :: MIT License
Classifier: Programming Language :: Python
Classifier: Programming Language :: Python :: 3
Classifier: Programming Language :: Python :: 3.9
Classifier: Topic :: Software Development :: Libraries :: Python Modules
Provides-Extra: cli
Provides-Extra: devtools
Provides-Extra: docs
Requires-Dist: PyYAML (>=5.4.1,<6.0.0)
Requires-Dist: blacken-docs (>=1.12.0,<2.0.0); extra == "docs"
Requires-Dist: boto3 (>=1.17.80,<2.0.0)
Requires-Dist: click-completion[cli] (>=0.5.2,<0.6.0); extra == "cli"
Requires-Dist: click[cli] (>=8.0.1,<9.0.0); extra == "cli"
Requires-Dist: dacite (>=1.6.0,<2.0.0)
Requires-Dist: graphviz (>=0.16,<0.17)
Requires-Dist: ipdb (>=0.13.8,<0.14.0); extra == "devtools"
Requires-Dist: mkdocs (>=1.1.2,<2.0.0); extra == "docs"
Requires-Dist: mkdocs-git-revision-date-localized-plugin (>=0.9.2,<0.10.0); extra == "docs"
Requires-Dist: mkdocs-macros-plugin (>=0.5.5,<0.6.0); extra == "docs"
Requires-Dist: mkdocs-material (>=7.1.5,<8.0.0); extra == "docs"
Requires-Dist: notebook (>=6.4.0,<7.0.0); extra == "devtools"
Requires-Dist: pre-commit (>=2.13.0,<3.0.0); extra == "devtools"
Requires-Dist: pyhumps (>=3.0.2,<4.0.0)
Requires-Dist: structlog (>=21.1.0,<22.0.0)
Project-URL: Changelog, https://github.com/timoguin/aws-data-tools-py/blob/master/CHANGELOG.md
Project-URL: Documentation, https://timoguin.github.io/aws-data-tools-py
Project-URL: Repository, https://github.com/timoguin/aws-data-tools-py
Project-URL: Source, https://github.com/timoguin/aws-data-tools-py
Project-URL: Tracker, https://github.com/timoguin/aws-data-tools-py/issues
